[{"fecha": "2024-07-15 06:30:21", "instruccion": "{\"datos_red\":{\"op\":\"UPDATE\",\"set\":\" fech_pag='2024-06-30' \",\"filtro\":\" coduser='465'\"},\"histori_pags\":{\"op\":\"INSERT INTO\",\"set\":\"coduser, fech_pag, cant_Bf, fech_venc, anfit\",\"filtro\":\" (465, '2024-07-15', 150000, '2024-07-31', '::1')\"},\"datos_per\":{\"op\":\"UPDATE\",\"set\":\" fech_ing='2024-07-15', fech_ven='2024-07-31' \",\"filtro\":\" coduser='465'\"}}", "firma": "22e1c1ac9905218489931f40a5b6e9d7e7f1289a"}, {"fecha": "2024-07-15 10:22:23", "instruccion": "{\"datos_red\":{\"op\":\"UPDATE\",\"set\":\" fech_pag='2024-09-13' \",\"filtro\":\" coduser='341'\"},\"histori_pags\":{\"op\":\"INSERT INTO\",\"set\":\"coduser, fech_pag, cant_Bf, fech_venc, anfit\",\"filtro\":\" (341, '2024-07-15', 600000, '2024-10-14', '::1')\"},\"datos_per\":{\"op\":\"UPDATE\",\"set\":\" fech_ing='2024-07-15', fech_ven='2024-10-14' \",\"filtro\":\" coduser='341'\"}}", "firma": "da962705e5bcde575a016d633918e4a89578464b"}, {"fecha": "2024-07-17 16:45:04", "instruccion": "{\"histori_pags\":{\"op\":\"delete from\",\"set\":\" coduser='465' and fech_venc='2024-07-31'\",\"filtro\":\"\"},\"datos_red\":{\"op\":\"update\",\"set\":\" fech_pag='2024-06-16' \",\"filtro\":\" coduser='465'\"},\"datos_per\":{\"op\":\"update\",\"set\":\" fech_ven='2024-07-16', fech_ing='2024-06-30' \",\"filtro\":\" coduser='465'\"}}", "firma": "75793430f57c9fa110aa4cb177d23a3003142d56"}, {"fecha": "2024-07-17 17:03:03", "instruccion": "{\"datos_red\":{\"op\":\"UPDATE\",\"set\":\" fech_pag='2024-07-02' \",\"filtro\":\" coduser='465'\"},\"histori_pags\":{\"op\":\"INSERT INTO\",\"set\":\"coduser, fech_pag, cant_Bf, fech_venc, anfit\",\"filtro\":\" (465, '2024-07-17', 150000, '2024-08-02', '::1')\"},\"datos_per\":{\"op\":\"UPDATE\",\"set\":\" fech_ing='2024-07-17', fech_ven='2024-08-02' \",\"filtro\":\" coduser='465'\"}}", "firma": "056ee2db54a842adc9870c4b0b189544a67138ec"}]