[{"fecha": "2023-03-02 08:40:56", "instruccion": "{\"datos_red\":{\"op\":\"update\",\"set\":\" dir_mac='88:52:eb:20:41:80' \",\"filtro\":\" dir_ip='192.168.40.095'\"}}", "firma": "9fad5987657219afa945ffddb60915866b2a267c"}, {"fecha": "2023-03-02 08:40:56", "instruccion": "{\"datos_red\":{\"op\":\"update\",\"set\":\" dir_mac='c0:17:4d:bc:f0:07' \",\"filtro\":\" dir_ip='192.168.40.096'\"}}", "firma": "d8fcef8bd8a153ae4dbe250b5b76b5c30bea6fd1"}, {"fecha": "2023-03-02 08:40:56", "instruccion": "{\"datos_red\":{\"op\":\"update\",\"set\":\" dir_mac='c4:c6:13:91:ab:6b', fech_pag='2023-02-09', coduser='340' \",\"filtro\":\" dir_ip='192.168.40.111'\"}}", "firma": "9797e41d3a42d88bac8126b176c75db0ad097dea"}]