[{"fecha": "2022-08-14 06:20:29", "instruccion": "{\"datos_red\":{\"op\":\"UPDATE\",\"set\":\" fech_pag='2022-08-14' \",\"filtro\":\" coduser='312'\"},\"histori_pags\":{\"op\":\"INSERT INTO\",\"set\":\"coduser, fech_pag, cant_Bf, fech_venc, anfit\",\"filtro\":\" (312, '2022-08-14', 200000, '2022-09-14', '::1')\"},\"datos_per\":{\"op\":\"UPDATE\",\"set\":\" fech_ing='2022-08-14', fech_ven='2022-09-14' \",\"filtro\":\" coduser='312'\"}}", "firma": "840e8811f9aae6e76c7fc49dfe6cb2b16b26d234"}, {"fecha": "2022-08-14 06:21:11", "instruccion": "{\"datos_red\":{\"op\":\"update\",\"set\":\" dir_mac='00:00:00:00:00:00', fech_pag='2008-01-01', coduser=0 \",\"filtro\":\" dir_ip='192.168.40.017'\"}}", "firma": "2fe2235bfa2c7e16a3ab3b7349059c7a42e7908e"}, {"fecha": "2022-08-14 06:21:11", "instruccion": "{\"datos_red\":{\"op\":\"update\",\"set\":\" dir_mac='00:00:00:00:00:00', fech_pag='2008-01-01', coduser=0 \",\"filtro\":\" dir_ip='192.168.40.051'\"}}", "firma": "362a0771c6268e598d56346735c4c36b275947bf"}, {"fecha": "2022-08-14 06:21:11", "instruccion": "{\"datos_red\":{\"op\":\"update\",\"set\":\" dir_mac='00:00:00:00:00:00', fech_pag='2008-01-01', coduser=0 \",\"filtro\":\" dir_ip='192.168.45.090'\"}}", "firma": "156581d1d699ac248451d0a69d764e7d70143e7e"}, {"fecha": "2022-08-14 06:21:11", "instruccion": "{\"datos_red\":{\"op\":\"update\",\"set\":\" dir_mac='e8:94:f6:c2:61:91', fech_pag='2022-08-14', coduser='312' \",\"filtro\":\" dir_ip='192.168.40.017'\"}}", "firma": "973a27151eda0294dae52eb394a1d1c3f882bf9e"}, {"fecha": "2022-08-14 06:21:11", "instruccion": "{\"datos_red\":{\"op\":\"update\",\"set\":\" dir_mac='00:00:00:00:00:00', fech_pag='2008-01-01', coduser=0 \",\"filtro\":\" dir_ip='192.168.45.170'\"}}", "firma": "ae23f0d44d13928fb6d5ea017ba563bcb3ec6300"}]