[{"fecha": "2022-07-30 11:44:57", "instruccion": "{\"datos_red\":{\"op\":\"UPDATE\",\"set\":\" fech_pag='2022-07-31' \",\"filtro\":\" coduser='296'\"},\"histori_pags\":{\"op\":\"INSERT INTO\",\"set\":\"coduser, fech_pag, cant_Bf, fech_venc, anfit\",\"filtro\":\" (296, '2022-07-30', 200000, '2022-08-31', '::1')\"},\"datos_per\":{\"op\":\"UPDATE\",\"set\":\" fech_ing='2022-07-30', fech_ven='2022-08-31' \",\"filtro\":\" coduser='296'\"}}", "firma": "6db29a71962d9740058154f4a8b5032aab0505cc"}, {"fecha": "2022-07-30 11:48:59", "instruccion": "{\"datos_red\":{\"op\":\"UPDATE\",\"set\":\" fech_pag='2022-07-30' \",\"filtro\":\" coduser='257'\"},\"histori_pags\":{\"op\":\"INSERT INTO\",\"set\":\"coduser, fech_pag, cant_Bf, fech_venc, anfit\",\"filtro\":\" (257, '2022-07-30', 200000, '2022-08-30', '::1')\"},\"datos_per\":{\"op\":\"UPDATE\",\"set\":\" fech_ing='2022-07-30', fech_ven='2022-08-30' \",\"filtro\":\" coduser='257'\"}}", "firma": "f90fa312d48b827aabb826214826967f202febcb"}]