[{"fecha": "2021-10-02 11:53:22", "instruccion": "{\"datos_red\":{\"op\":\"UPDATE\",\"set\":\" fech_pag='2021-10-07' \",\"filtro\":\" coduser='272'\"},\"histori_pags\":{\"op\":\"INSERT INTO\",\"set\":\"coduser, fech_pag, cant_Bf, fech_venc, anfit\",\"filtro\":\" (272, '2021-10-02', 200000, '2021-11-07', '181.78.4.253')\"},\"datos_per\":{\"op\":\"UPDATE\",\"set\":\" fech_ing='2021-10-02', fech_ven='2021-11-07' \",\"filtro\":\" coduser='272'\"}}", "firma": "b83263acc6591e4c5dfd1efc1fea28215ffa4465"}]