[{"fecha": "2021-12-23 09:22:50", "instruccion": "{\"datos_red\":{\"op\":\"UPDATE\",\"set\":\" fech_pag='2021-12-23' \",\"filtro\":\" coduser='369'\"},\"histori_pags\":{\"op\":\"INSERT INTO\",\"set\":\"coduser, fech_pag, cant_Bf, fech_venc, anfit\",\"filtro\":\" (369, '2021-12-23', 200000, '2022-01-23', '181.78.4.253')\"},\"datos_per\":{\"op\":\"UPDATE\",\"set\":\" fech_ing='2021-12-23', fech_ven='2022-01-23' \",\"filtro\":\" coduser='369'\"}}", "firma": "a1b622fffd7073252e4e9aeb54c96b787631c7d2"}]